README.rst
setup.py
toastedmarshmallow_models/__init__.py
toastedmarshmallow_models.egg-info/PKG-INFO
toastedmarshmallow_models.egg-info/SOURCES.txt
toastedmarshmallow_models.egg-info/dependency_links.txt
toastedmarshmallow_models.egg-info/not-zip-safe
toastedmarshmallow_models.egg-info/requires.txt
toastedmarshmallow_models.egg-info/top_level.txt