Metadata-Version: 1.1
Name: toastedmarshmallow-models
Version: 1.0.4
Summary: ['Class models with validation and serialization ', 'using toastedmarshmallow fields and validators.']
Home-page: https://gitlab.com/py-ddd/toastedmarshmallow-models
Author: Victor Klapholz
Author-email: victor.klapholz@gmail.com
License: apache2
Keywords: serialization,rest,json,api,marshal,marshalling,deserialization,validation,schema,toastedmarshmallow==0.2.6
Platform: UNKNOWN
Classifier: Development Status :: 5 - Production/Stable
Classifier: Intended Audience :: Developers
Classifier: License :: OSI Approved :: Apache Software License
Classifier: Programming Language :: Python :: 3.6
Classifier: Programming Language :: Python :: Implementation :: CPython
Classifier: Programming Language :: Python :: Implementation :: PyPy
